projhc/__init__.py
projhc/main.py
projhc/utils/__init__.py
projhc/utils/setup_django.py
project_help_create-1.0.0.dist-info/LICENSE
project_help_create-1.0.0.dist-info/METADATA
project_help_create-1.0.0.dist-info/WHEEL
project_help_create-1.0.0.dist-info/top_level.txt
project_help_create-1.0.0.dist-info/RECORD
