Metadata-Version: 2.1
Name: project-help-create
Version: 1.0.0
Summary: Helper for creating projects on python
Home-page: https://github.com/Egor-oop/projhc
Author: George
Author-email: gulidoegor@gmail.com
Project-URL: Bug Tracker, https://github.com/pypa/sampleproject/issues
Classifier: Programming Language :: Python :: 3
Classifier: License :: OSI Approved :: MIT License
Classifier: Operating System :: OS Independent
Requires-Python: >=3.6
License-File: LICENSE
